{"cameraMode":{"drawMode":0,"name":"Shaded","section":"Shading Mode"},"sceneLighting":false,"audioPlay":false,"sceneViewState":{"m_AlwaysRefresh":false,"showFog":true,"showSkybox":false,"showFlares":true,"showImageEffects":true,"showParticleSystems":true,"showVisualEffectGraphs":true,"m_FxEnabled":true},"in2DMode":false,"pivot":{"x":-52.0635871887207,"y":14.136859893798829,"z":22.92633628845215},"rotation":{"x":0.50578373670578,"y":0.02321855165064335,"z":-0.011524871923029423,"w":0.8639110326766968},"size":0.7998427152633667,"orthographic":false}