{"cameraMode":{"drawMode":0,"name":"Shaded","section":"Shading Mode"},"sceneLighting":false,"audioPlay":false,"sceneViewState":{"m_AlwaysRefresh":false,"showFog":true,"showSkybox":false,"showFlares":true,"showImageEffects":true,"showParticleSystems":true,"showVisualEffectGraphs":true,"m_FxEnabled":true},"in2DMode":false,"pivot":{"x":1.0723190307617188,"y":5.856428146362305,"z":0.0000019073486328125},"rotation":{"x":0.10232951492071152,"y":0.8469640612602234,"z":-0.1668773591518402,"w":0.49590152502059939},"size":28.487689971923829,"orthographic":false}