{"cameraMode":{"drawMode":0,"name":"Shaded","section":"Shading Mode"},"sceneLighting":false,"audioPlay":false,"sceneViewState":{"m_AlwaysRefresh":false,"showFog":true,"showSkybox":false,"showFlares":true,"showImageEffects":true,"showParticleSystems":true,"showVisualEffectGraphs":true,"m_FxEnabled":true},"in2DMode":false,"pivot":{"x":0.045775752514600757,"y":0.605056643486023,"z":-0.11839158087968826},"rotation":{"x":-0.037255868315696719,"y":-0.9512386322021484,"z":0.11451317369937897,"w":-0.2864430248737335},"size":0.6435779333114624,"orthographic":false}