{"cameraMode":{"drawMode":0,"name":"Shaded","section":"Shading Mode"},"sceneLighting":true,"audioPlay":false,"sceneViewState":{"m_AlwaysRefresh":false,"showFog":true,"showSkybox":true,"showFlares":true,"showImageEffects":true,"showParticleSystems":true,"showVisualEffectGraphs":true,"m_FxEnabled":true},"in2DMode":false,"pivot":{"x":75.09170532226563,"y":29.718130111694337,"z":-34.445579528808597},"rotation":{"x":0.014294780790805817,"y":-0.8153294920921326,"z":0.018093856051564218,"w":0.5820255279541016},"size":10.0,"orthographic":false}